sopel_arxiv/__init__.py
sopel_arxiv/arxiv.py
sopel_arxiv-1.0.0.dist-info/LICENSE
sopel_arxiv-1.0.0.dist-info/METADATA
sopel_arxiv-1.0.0.dist-info/WHEEL
sopel_arxiv-1.0.0.dist-info/entry_points.txt
sopel_arxiv-1.0.0.dist-info/top_level.txt
sopel_arxiv-1.0.0.dist-info/RECORD
