Metadata-Version: 2.1
Name: sopel-arxiv
Version: 1.0.0
Summary: An arXiv plugin for Sopel
Home-page: https://github.com/SnoopJ/sopel-arxiv
Author: SnoopJ
Author-email: snoopjedi@gmail.com
License: Eiffel Forum License, version 2
Classifier: Intended Audience :: Developers
Classifier: Intended Audience :: System Administrators
Classifier: License :: Eiffel Forum License (EFL)
Classifier: License :: OSI Approved :: Eiffel Forum License
Classifier: Topic :: Communications :: Chat :: Internet Relay Chat
License-File: LICENSE
Requires-Dist: sopel (>=7.1)
